ctproc/__init__.py
ctproc/ctbase.py
ctproc/ctconfig.py
ctproc/ctdocument.py
ctproc/ctmatch_main.py
ctproc/ctmatch_utils.py
ctproc/cttopic.py
ctproc/doc_checker.py
ctproc/eligibility.py
ctproc/lab_extractor.py
ctproc/proc.py
ctproc/regex_patterns.py
ctproc/skip_crit.py
ctproc/skip_ids.py
ctproc/stats.py
ctproc/utils.py
ctproc/scripts/bert_fine_tune.py
ctproc/scripts/indexing.py
ctproc/scripts/move_negs.py
ctproc/scripts/vis_scripts.py
ctproc/tests/__init__.py
ctproc/tests/ctproc_tests.py
ctproc/tests/test_doc.py
ctproc/tests/test_elig.py
ctproc/tests/test_topic.py
ctproc-0.2.3.dist-info/LICENSE
ctproc-0.2.3.dist-info/METADATA
ctproc-0.2.3.dist-info/WHEEL
ctproc-0.2.3.dist-info/top_level.txt
ctproc-0.2.3.dist-info/RECORD
